{
  "äddi": "https://lod.lu/uploads/OGG/addi2.ogg",
  "merci": "https://lod.lu/uploads/OGG/merci2.ogg",
  "wëllkomm": "https://lod.lu/uploads/OGG/wellkomm1.ogg",
  "pardon": "https://lod.lu/uploads/OGG/pardon2.ogg",
  "jo": "https://lod.lu/uploads/OGG/jo1.ogg",
  "nee": "https://lod.lu/uploads/OGG/nee1.ogg",
  "wéi": "https://lod.lu/uploads/OGG/wei3.ogg",
  "gär": "https://lod.lu/uploads/OGG/gar1.ogg",
  "bis": "https://lod.lu/uploads/OGG/bis1.ogg",
  "eent": "https://lod.lu/uploads/OGG/eent1.ogg",
  "zwee": "https://lod.lu/uploads/OGG/zwee2.ogg",
  "dräi": "https://lod.lu/uploads/OGG/drai1.ogg",
  "véier": "https://lod.lu/uploads/OGG/veier1.ogg",
  "fënnef": "https://lod.lu/uploads/OGG/fennef1.ogg",
  "sechs": "https://lod.lu/uploads/OGG/sechs1.ogg",
  "siwen": "https://lod.lu/uploads/OGG/siwen1.ogg",
  "aacht": "https://lod.lu/uploads/OGG/aacht1.ogg",
  "néng": "https://lod.lu/uploads/OGG/neng1.ogg",
  "zéng": "https://lod.lu/uploads/OGG/zeng1.ogg",
  "papp": "https://lod.lu/uploads/OGG/papp1.ogg",
  "mamm": "https://lod.lu/uploads/OGG/mamm1.ogg",
  "kand": "https://lod.lu/uploads/OGG/kand1.ogg",
  "jong": "https://lod.lu/uploads/OGG/jong2.ogg",
  "meedchen": "https://lod.lu/uploads/OGG/meedchen1.ogg",
  "frau": "https://lod.lu/uploads/OGG/fra1.ogg",
  "mann": "https://lod.lu/uploads/OGG/mann3.ogg",
  "brudder": "https://lod.lu/uploads/OGG/brudder1.ogg",
  "schwëster": "https://lod.lu/uploads/OGG/schwester1.ogg",
  "grousselteren": "https://lod.lu/uploads/OGG/grousselteren1.ogg",
  "haus": "https://lod.lu/uploads/OGG/haus1.ogg",
  "dier": "https://lod.lu/uploads/OGG/dier2.ogg",
  "fënster": "https://lod.lu/uploads/OGG/fenster1.ogg",
  "buch": "https://lod.lu/uploads/OGG/buch2.ogg",
  "stull": "https://lod.lu/uploads/OGG/stull1.ogg",
  "dësch": "https://lod.lu/uploads/OGG/desch1.ogg",
  "auto": "https://lod.lu/uploads/OGG/auto1.ogg",
  "telefon": "https://lod.lu/uploads/OGG/telefon1.ogg",
  "waasser": "https://lod.lu/uploads/OGG/waasser2.ogg",
  "kaffi": "https://lod.lu/uploads/OGG/kaffi1.ogg",
  "dag": "https://lod.lu/uploads/OGG/dag1.ogg",
  "nuecht": "https://lod.lu/uploads/OGG/nuecht1.ogg",
  "mëtteg": "https://lod.lu/uploads/OGG/metteg1.ogg",
  "owes": "https://lod.lu/uploads/OGG/owes1.ogg",
  "sonn": "https://lod.lu/uploads/OGG/sonn1.ogg",
  "mound": "https://lod.lu/uploads/OGG/mound1.ogg",
  "stierm": "https://lod.lu/uploads/OGG/stiermen2.ogg",
  "reen": "https://lod.lu/uploads/OGG/reen1.ogg",
  "schnéi": "https://lod.lu/uploads/OGG/schnei1.ogg",
  "loft": "https://lod.lu/uploads/OGG/loft1.ogg"
}